setup.py
pygrt/__init__.py
pygrt/pygrt.py
pygrt.egg-info/PKG-INFO
pygrt.egg-info/SOURCES.txt
pygrt.egg-info/dependency_links.txt
pygrt.egg-info/requires.txt
pygrt.egg-info/top_level.txt
pygrt/api/Api.py
pygrt/api/Bus.py
pygrt/api/Route.py
pygrt/api/__init__.py