Metadata-Version: 1.0
Name: pygrt
Version: 1.0.0
Summary: Thin API wrapper for GRT Realtime API
Home-page: UNKNOWN
Author: Harley Benoit (@s0i)
Author-email: UNKNOWN
License: UNKNOWN
Platform: UNKNOWN
